Metadata-Version: 2.1
Name: course-runner
Version: 0.2.1
Summary: autOevaluate yoUr Student Easily
Home-page: https://gitlab.com/course-autoevaluate/runner
Author: Thibault Falque
Author-email: thibault.falque@univ-artois.fr
License: LGPLv3+
Keywords: autoevaluate
Platform: UNKNOWN
Classifier: Programming Language :: Python :: 3.9
Classifier: License :: OSI Approved :: GNU Lesser General Public License v3 or later (LGPLv3+)
Classifier: Development Status :: 4 - Beta
Classifier: Operating System :: OS Independent
License-File: LICENSE
